pycomma/__init__.py
pycomma/comma.py
pycomma-0.1.3.dist-info/LICENSE
pycomma-0.1.3.dist-info/METADATA
pycomma-0.1.3.dist-info/WHEEL
pycomma-0.1.3.dist-info/top_level.txt
pycomma-0.1.3.dist-info/RECORD
